[
  {
    "year": 2019,
    "section_name": "单项选择题",
    "section_type": "single",
    "number": 1,
    "stem": "企业目标资本结构是使加权平均资本成本最低的资本结构。假设其他条件不变,该资本结构也是( )。",
    "options": {
      "A": "使利润最大的资本结构",
      "B": "使每股收益最高的资本结构",
      "C": "使股东财富最大的资本结构",
      "D": "使股票价格最高的资本结构"
    },
    "answer": "C",
    "analysis": "从根本上讲，财务管理的目标在于追求股东财富最大化。企业最佳的目标资本结构下，企业价值达到最大，此时的加权平均资本成本也达到最低。也就是说，企业在目标资本结构下的股东投资成本和债务价值是相对确定的，此时公司价值最大化也就是股东财富最大化，选项C正确。",
    "source": {
      "question_text": "2019_财务成本管理_题目.txt",
      "answer_text": "2019_财务成本管理_答案.txt"
    }
  },
  {
    "year": 2019,
    "section_name": "单项选择题",
    "section_type": "single",
    "number": 2,
    "stem": "甲公司处于可持续增长状态。2019年初总资产1000万元，总负债200万元，预计2019年净利润100万元，股利支付率20%。甲公司2019年可持续增长率是( )。",
    "options": {
      "A": "2.5%",
      "B": "8%",
      "C": "10%",
      "D": "11.1%"
    },
    "answer": "C",
    "analysis": "可持续增长率=本期净利润×本期利润留存率÷期初股东权益=100×（1-20%）÷（1000-200）=10%，选项C正确。正确。",
    "source": {
      "question_text": "2019_财务成本管理_题目.txt",
      "answer_text": "2019_财务成本管理_答案.txt"
    }
  },
  {
    "year": 2019,
    "section_name": "单项选择题",
    "section_type": "single",
    "number": 3,
    "stem": "甲商场进行分期付款销售活动，某款手机可在半年内分6 期付款，每期期初付款 600元。假设年利率 12%。该手机价款如果购买时一次性付清，下列各项金额中最接近的是( )元。",
    "options": {
      "A": "2912",
      "B": "3437",
      "C": "3477",
      "D": "3512"
    },
    "answer": "D",
    "analysis": "报价利率=12%，计息期利率=12%/12=1%，预付年金现值系数为（P/A，i，n-1）+1，故P=A×［（P/A，1%，6-1）+1］=600×（4.8534+1）=3512（元） 或P=A×［（P/A，1%，6）×（1+1%）］=600×［5.7955×（1+1%）］=3512（元），选项D",
    "source": {
      "question_text": "2019_财务成本管理_题目.txt",
      "answer_text": "2019_财务成本管理_答案.txt"
    }
  },
  {
    "year": 2019,
    "section_name": "单项选择题",
    "section_type": "single",
    "number": 4,
    "stem": "甲公司有 X、Y 两个项目组，分别承接不同的项目类型。X 项目组资本成本 10%，Y 项目组资本成本 14%，甲公司资本成本12%。下列项目中，甲公司可以接受的是( )。",
    "options": {
      "A": "报酬率为9%的X类项目",
      "B": "报酬率为11%的 X类项目",
      "C": "报酬率为12%的 Y类项目",
      "D": "报酬率为13%的 Y类项目"
    },
    "answer": "B",
    "analysis": "因为项目的风险与公司整体风险不同，所以项目的资本成本与公司的资本成本不同，因此不能使用公司的资本成本作为评价项目是否可以接受的标准。当投资项目的报酬率大于项目的资本成本时，项目是可以接受的，X 项目组的资本成本为10%，报酬率为 9%的 X 类项目小于项目资本成本，不可以接受，选项 A错误；报酬率为11%的X类项目大于项目资本成本，可以接受，选项B正确；Y 项目组的资本成本为 14%，报酬率为12%和13%的 Y类项目的报酬率均小于项目的资本成本，选项CD错误。",
    "source": {
      "question_text": "2019_财务成本管理_题目.txt",
      "answer_text": "2019_财务成本管理_答案.txt"
    }
  },
  {
    "year": 2019,
    "section_name": "单项选择题",
    "section_type": "single",
    "number": 5,
    "stem": "甲、乙公司已进入稳定增长状态，股票信息如下：甲乙期望报酬率 10% 14% 股利稳定增长率 6% 10% 股票价格 30元 40元下列关于甲、乙股票投资的说法中,正确的是( )。",
    "options": {
      "A": "甲、乙股票预期股利相同",
      "B": "甲、乙股票股利收益率相同",
      "C": "甲、乙股票预期资本利得相同",
      "D": "甲、乙股票资本利得收益率相同"
    },
    "answer": "B",
    "analysis": "根据公式，股票的期望报酬率=D1/P0+g，可得：甲股票的预期股利为1.2元，乙股票的预期股利为1.6元，甲、乙股票预期股利不相同，选项A 错误；根据公式，股利收益率=期望报酬率-资本利得收益率，可得：甲、乙股票的股利收益率均为4%，选项B正确；甲股票的预计价格为 30×（1+6%）＝31.8 （元），预期的资本利得为1.8元，乙股票的预计价格为 40×（1+10%）＝44（元），预期的资本利得为4元，甲、乙股票预期资本利得不相同，选项C 错误；资本利得收益率＝股利增长率，甲股票的为6%，乙股票为 10%，甲、乙股票资本利得收益率不相同，选项D错误。",
    "source": {
      "question_text": "2019_财务成本管理_题目.txt",
      "answer_text": "2019_财务成本管理_答案.txt"
    }
  },
  {
    "year": 2019,
    "section_name": "单项选择题",
    "section_type": "single",
    "number": 6,
    "stem": "假设其他条件不变，下列影响期权价值的各项因素中，会引起期权价值同向变动的是( )。",
    "options": {
      "A": "执行价格",
      "B": "无风险利率",
      "C": "标的股票市价",
      "D": "标的股票股价波动率"
    },
    "answer": "D",
    "analysis": "执行价格的高低与看涨期权价值反向变动，与看跌期权价值同向变动，选项A错误；无风险利率与看涨期权价值同向变动，与看跌期权价值反向变动，选项B错误；标的股票市价与看涨期权价值同向变动，与看跌期权价值反向变动，选项C错误；期权持有者的最大损失均以期权费为限，而股价波动越剧烈，其可能获得的收益越高，因此股价波动率的增加会使期权价值增加，选项D正确。",
    "source": {
      "question_text": "2019_财务成本管理_题目.txt",
      "answer_text": "2019_财务成本管理_答案.txt"
    }
  },
  {
    "year": 2019,
    "section_name": "单项选择题",
    "section_type": "single",
    "number": 7,
    "stem": "甲公司股票每股10元，以配股价格每股8元向全体股东每10股配售10股。拥甲公司80%股权的投资者行使了配股权。乙持有甲公司股票1000股，未行使配股权，配股除权使乙的财富( )。",
    "options": {
      "A": "增加220元",
      "B": "减少890元",
      "C": "减少1000元",
      "D": "不发生变化"
    },
    "answer": "B",
    "analysis": "股份变动比例为0.8，配股后每股价格＝（10＋0.8×8）/（1＋0.8）＝9.11（元），股东配股后乙拥有的股票价值＝9.11×1000＝9110（元），股东财富损失＝1000×10－9110＝890（元），选项B 正确。方法 2：甲公司在淡季时，易变现率=［（股东权益+长期债务+经营性流动负债）-长期资产］/经营性流动资产=［2000-（1000+200）］/（300+200+500）=0.8，其在淡季时易变现率小于1，故其属于激进型",
    "source": {
      "question_text": "2019_财务成本管理_题目.txt",
      "answer_text": "2019_财务成本管理_答案.txt"
    }
  },
  {
    "year": 2019,
    "section_name": "单项选择题",
    "section_type": "single",
    "number": 8,
    "stem": "甲公司是一家啤酒生产企业，淡季需占用300万元货币资金、200万元应收账款、500万元存货、1000万元固定资产以及200万元无形资产（除此以外无其他资产），旺季需额外增加300万元季节性存货。经营性流动负债、长期负债和股东权益总额始终保持在2000万元，其余靠短期借款提供资金。甲公司的营运资本筹资策略是( )。",
    "options": {
      "A": "保守型策略",
      "B": "适中型策略",
      "C": "激进型策略",
      "D": "无法确定"
    },
    "answer": "C",
    "analysis": "方法1：甲公司在淡季时，稳定性流动资产+长期资产=300+200+500+1000+200=2200（万元）；长期资本=2000（万元），长期资本＜稳定性流动资产+长期资产，则剩余部分需要由短期金融负债解决，所以甲公司采用的是激进型筹资策略，选项C 正确。筹资策略。",
    "source": {
      "question_text": "2019_财务成本管理_题目.txt",
      "answer_text": "2019_财务成本管理_答案.txt"
    }
  },
  {
    "year": 2019,
    "section_name": "单项选择题",
    "section_type": "single",
    "number": 9,
    "stem": "甲工厂生产联产品X 和 Y，9月份产量分别为690 件和 1000 件，分离点前发生联合成本40000元，分离点后分别发生深加工成本10000元和18000元，X和Y的最终销售总价分别为970000元和1458000元。按照可变现净值法，x和Y的总加工成本分别是( )。",
    "options": {
      "A": "12000元和28000元",
      "B": "16000元和24000元",
      "C": "22000元和46000元",
      "D": "26000元和42000元"
    },
    "answer": "D",
    "analysis": "X产品的可变现净值=970000-10000=960000（元）；Y产品的可变现净值=1458000-18000=1440000（元）。产品的总加工成本=分摊至该产品的分离点前联合成本+分离点后的深加工成本。X 产品的总加工成本=40000×［960000/（960000+1440000）］+10000=26000（元）；Y 产品的总加工成本=40000×［1440000/（960000+1440000）］+18000=42000（元），选项D正确。",
    "source": {
      "question_text": "2019_财务成本管理_题目.txt",
      "answer_text": "2019_财务成本管理_答案.txt"
    }
  },
  {
    "year": 2019,
    "section_name": "单项选择题",
    "section_type": "single",
    "number": 10,
    "stem": "下列关于平行结转分步法的说法中，正确的是( )。",
    "options": {
      "A": "平行结转分步法在产品是尚未最终完成的产品",
      "B": "平行结转分步法适用于经常对外销售半成品的企业",
      "C": "平行结转分步法有利于考察在产品存货资金占用情况",
      "D": "平行结转分步法有利于各步骤在产品的实务管理和成本管理"
    },
    "answer": "A",
    "analysis": "采用平行结转分步法下，完工产品是指企业最终完工的产成品，某步骤在产品是指该步骤尚未加工完成的在产品和该步骤已完工但尚未最终完成的产品，选项 A 正确；平行结转分步法不能提供各个步骤的半成品成本资料，所以不适合于经常对外销售半成品的企业，选项B错误；在平行结转分步法下，在产品的费用在产品最后完成以前，不随实物转出而转出，即不按其所在的地点登记，而按其发生的地点登记，因而不能为各个生产步骤在产品的实物管理提供资料，也不利于考察在产品存货资金占用情况，选项CD 错误。",
    "source": {
      "question_text": "2019_财务成本管理_题目.txt",
      "answer_text": "2019_财务成本管理_答案.txt"
    }
  },
  {
    "year": 2019,
    "section_name": "单项选择题",
    "section_type": "single",
    "number": 11,
    "stem": "电信运营商推出“手机 10元保号，可免费接听电话和接收短信，主叫国内通话每分钟0.2元”的套餐业务，选用该套餐的消费者每月手机费属于( )。",
    "options": {
      "A": "半变动成本",
      "B": "固定成本",
      "C": "阶梯式成本",
      "D": "延期变动成本"
    },
    "answer": "A",
    "analysis": "半变动成本是在初始成本的基础上随业务量正比例增长的成本，该套餐消费的初始成本为10元，在10元的基础之上，每通话1分钟，增加0.2元的费用，所以该套餐费属于半变动成本，选项A 正确。",
    "source": {
      "question_text": "2019_财务成本管理_题目.txt",
      "answer_text": "2019_财务成本管理_答案.txt"
    }
  },
  {
    "year": 2019,
    "section_name": "单项选择题",
    "section_type": "single",
    "number": 12,
    "stem": "甲公司是一家汽车制造企业，每年需要M 零部件 20000 个，可以自制或外购。自制时直接材料400元/个，直接人工 100元/个，变动制造费用 200元/个，固定制造费用 150元/个。甲公司有足够的生产能力，如不自制，设备出租可获得年租金400000元甲公司选择外购的条件是单价小于( )元。",
    "options": {
      "A": "680",
      "B": "720",
      "C": "830",
      "D": "870"
    },
    "answer": "B",
    "analysis": "本题中，固定制造费用为非相关成本，不应予以考虑。自制的单位变动成本=400+100+200=700（元），选择外购的临界单价=700+400000÷20000=720（元），选项B 正确。",
    "source": {
      "question_text": "2019_财务成本管理_题目.txt",
      "answer_text": "2019_财务成本管理_答案.txt"
    }
  },
  {
    "year": 2019,
    "section_name": "单项选择题",
    "section_type": "single",
    "number": 13,
    "stem": "甲公司正在编制直接材料预算，预计单位产成品材料消耗量10 千克，材料价格 50元/千克；第一季度期初、期末材料存货分别为500千克和550千克；第一季度、第二季度产成品销量分别为200件和250 件；期末产成品存货按下季度销量10%安排。预计第一季度材料采购金额是( )元。",
    "options": {
      "A": "100000",
      "B": "102500",
      "C": "105000",
      "D": "130000"
    },
    "answer": "C",
    "analysis": "第一季度末产成品数量＝250×10＝25（件），第一季度初产成品数量＝200×10%＝20（件），第一季度生产量＝200＋25－20＝205（件），材料生产需要量＝205×10＝2050（千克），第一季度材料采购量＝2050＋550－500＝2100（千克），预计第一季度材料采购金额＝2100×50＝105000（元），选项C正确。",
    "source": {
      "question_text": "2019_财务成本管理_题目.txt",
      "answer_text": "2019_财务成本管理_答案.txt"
    }
  },
  {
    "year": 2019,
    "section_name": "单项选择题",
    "section_type": "single",
    "number": 14,
    "stem": "甲公司销售收入50万元，边际贡献率30%。该公司仅设K和 W两个部门，其中K部门的变动成本30万元，边际贡献率25%。下列说法中，错误的是( )。",
    "options": {
      "A": "K 部门变动成本率为70%",
      "B": "K 部门边际贡献为10万元",
      "C": "W 部门边际贡献率为50%",
      "D": "W 部门销售收入为10万元"
    },
    "answer": "A",
    "analysis": "",
    "source": {
      "question_text": "2019_财务成本管理_题目.txt",
      "answer_text": "2019_财务成本管理_答案.txt"
    }
  },
  {
    "year": 2019,
    "section_name": "多项选择题",
    "section_type": "multiple",
    "number": 1,
    "stem": "甲投资组合由证券X 和证券Y各占50%组成。下列说法中，正确的有( )。",
    "options": {
      "A": "甲的β系数=X的β系数×50%+Y的β系数×50%",
      "B": "甲的期望报酬率=X的期望报酬率×50%+Y期望报酬率×50%",
      "C": "甲期望报酬率的标准差=X的期望报酬率的标准差×50%+Y期望报酬率的标准差×50%",
      "D": "甲期望报酬率的变异系数=X的期望报酬率的变异系数×50%+Y期望报酬率的变异系数×50%"
    },
    "answer": "AB",
    "analysis": "（1）β 系数衡量的是不可分散的系统风险，投资组合的 β 系数是组合内各单项证券 β 值的加权平均数，选项A正确；（2）两种或两种以上证券的组合，其期望报酬率为单个证券期望报酬率的加权平均数，选项B正确；（3）标准差衡量的是总风险，证券组合的标准差不是单个证券标准差的简单加权平均，因为证券组合的风险不仅取决于组合内的各证券的风险，还取决于各个证券之间的关系，选项CD 错误。",
    "source": {
      "question_text": "2019_财务成本管理_题目.txt",
      "answer_text": "2019_财务成本管理_答案.txt"
    }
  },
  {
    "year": 2019,
    "section_name": "多项选择题",
    "section_type": "multiple",
    "number": 2,
    "stem": "甲公司拟在华东地区建立一家专卖店，经营期限6年，资本成本8%。假设该投资的初始现金流量发生在期初，营业现金流量均发生在投产后各年末。该投资现值指数小于1，下列关于该投资的说法中，正确的有( )。",
    "options": {
      "A": "净现值小于0",
      "B": "内含报酬率小于8%",
      "C": "折现回收期小于6年",
      "D": "会计报酬率小于8%"
    },
    "answer": "AB",
    "analysis": "对于单一投资项目，现值指数小于1，则净现值小于0，内含报酬率小于资本成本，项目不可行，选项 AB 正确；因为净现值小于0，所以折现回收期不可能小于项目经营期6年，选项 C 错误；会计报酬率使用账面利润而非现金流量，忽视了折旧对现金流量的影响，忽视了净利润的时间分布对项目经济价值的影响，无法直接与资本成本进行比较，选项D 错误。",
    "source": {
      "question_text": "2019_财务成本管理_题目.txt",
      "answer_text": "2019_财务成本管理_答案.txt"
    }
  },
  {
    "year": 2019,
    "section_name": "多项选择题",
    "section_type": "multiple",
    "number": 3,
    "stem": "优先股股东比普通股股东的优先权体现在( )。",
    "options": {
      "A": "优先获得股息",
      "B": "优先取得剩余财产",
      "C": "优先出席股东大会",
      "D": "公司重大决策的优先表决权"
    },
    "answer": "AB",
    "analysis": "在公司分配利润时，优先股股息通常固定且优先支付；当企业面临破产时，优先股股东的求偿权优先于普通股股东，因此选项AB正确。",
    "source": {
      "question_text": "2019_财务成本管理_题目.txt",
      "answer_text": "2019_财务成本管理_答案.txt"
    }
  },
  {
    "year": 2019,
    "section_name": "多项选择题",
    "section_type": "multiple",
    "number": 4,
    "stem": "甲公司股票目前每股20元，市场上有X、Y两种该股票的看涨期权，执行价格分别为15元、25元，到期日相同。下列说法中，正确的有( )。",
    "options": {
      "A": "X 期权内在价值5元",
      "B": "Y 期权时间溢价0元",
      "C": "X 期权价值高于Y期权价值",
      "D": "股票价格上涨5元，X、Y 期权内在价值均上涨5元"
    },
    "answer": "AC",
    "analysis": "目前X看涨期权的内在价值=20-15=5（元），Y看涨期权的执行价格高于目前的股票市价，因此 Y看涨期权处于虚值状态，其内在价值=0，选项A 正确；期权价值=内在价值+时间溢价，该股票的两种期权到期日相同，因此波动率相同，从而时间的溢价相同，选项C 正确；因为期权尚未到期，所以时间溢价大于 0，选项B 错误；股票价格上涨5元，X 期权的内在价值=25-15=10元，Y 期权的内在价值=0元（目前Y 期权处于虚值状态，内在价值=0元），选项D错误。",
    "source": {
      "question_text": "2019_财务成本管理_题目.txt",
      "answer_text": "2019_财务成本管理_答案.txt"
    }
  },
  {
    "year": 2019,
    "section_name": "多项选择题",
    "section_type": "multiple",
    "number": 5,
    "stem": "甲公司2019年9月30日资产负债表显示，总资产100亿元，所有者权益50亿元，总股数5亿股。当日甲公司股票收盘价每股25元。下列关于当日甲公司股权价值的说法中，正确的有( )。",
    "options": {
      "A": "会计价值是50亿元",
      "B": "清算价值是50亿元",
      "C": "持续经营价值是100亿元",
      "D": "现时市场价值是125亿元"
    },
    "answer": "AD",
    "analysis": "会计价值是指账面价值，选项A正确；企业停止经营，出售资产产生的现金流，称为清算价值，选项B错误；由营业所产生的未来现金流量的现值，称为持续经营价值，选项C 错误；现时市场价值=5×25=125（亿元），选项D正确。",
    "source": {
      "question_text": "2019_财务成本管理_题目.txt",
      "answer_text": "2019_财务成本管理_答案.txt"
    }
  },
  {
    "year": 2019,
    "section_name": "多项选择题",
    "section_type": "multiple",
    "number": 6,
    "stem": "下列关于有企业所得税情况下MM理论的说法中，正确的有( )。",
    "options": {
      "A": "高杠杆企业的价值大于低杠杆企业的价值",
      "B": "高杠杆企业的债务资本成本大于低杠杆企业的债务资本成本",
      "C": "高杠杆企业的权益资本成本大于低杠杆企业的权益资本成本",
      "D": "高杠杆企业的加权平均资本成本大于低杠杆企业的加权平均资本成本"
    },
    "answer": "AC",
    "analysis": "债务利息可以在税前扣除，相当于增加了企业的现金流，因此随着企业负债比例的提高，企业价值也随之提高，在理论上全部融资来源于负债时，企业价值达到最大，选项A正确；有税的MM理论下，因存在债务利息抵税收益，因此高杠杆企业的债务资本成本小于低杠杆企业的债务资本成本，选项B 错误；有负债企业权益资本成本等于无负债企业的权益资本成本加上风险溢价，风险溢价与以市值计算的财务杠杆成正比，因而有负债企业的权益资本成本随着财务杠杆的提高而增加，选项C正确；在考虑所得税条件下，企业使用债务筹资时所支付的利息成本有一部分被利息抵税所抵消，有负债企业的加权平均资本成本随着债务筹资比例的增加而降低，选项D错误。",
    "source": {
      "question_text": "2019_财务成本管理_题目.txt",
      "answer_text": "2019_财务成本管理_答案.txt"
    }
  },
  {
    "year": 2019,
    "section_name": "多项选择题",
    "section_type": "multiple",
    "number": 7,
    "stem": "为确保债券平价发行，假设其他条件不变，下列各项可导致票面利率降低的有( )。",
    "options": {
      "A": "附认股权证",
      "B": "附转换条款",
      "C": "附赎回条款",
      "D": "附回售条款"
    },
    "answer": "ABD",
    "analysis": "发行附认股权证债券，可以以潜在的股权稀释为代价换取较低的利息，选项A正确。附转换条款的债券为可转换债券，其可以使得公司能够以较低的利率取得资金。因债权人有机会分享公司未来发展带来的收益，所以可转换债券的票面利率低于同一条件下的普通债券的利率，降低了公司前期的筹资成本，选项B正确。设置赎回条款是为了促使债券持有人转换股份，因此又被称为加速条款，赎回权是发行方的权利，需要以较高的利率才能吸引到投资人，选项C错误。设置回售条款可以保护债券投资人的利益，使他们能够避免遭受过大的投资损失，从而降低投资风险。回售权是给到债券持有方的权利，发行方因此可以较低的利率取得资金，选项D正确。",
    "source": {
      "question_text": "2019_财务成本管理_题目.txt",
      "answer_text": "2019_财务成本管理_答案.txt"
    }
  },
  {
    "year": 2019,
    "section_name": "多项选择题",
    "section_type": "multiple",
    "number": 8,
    "stem": "甲公司釆用成本分析模式确定最佳现金持有量。下列说法中,正确的有( )。",
    "options": {
      "A": "现金机会成本和管理成本相等时的现金持有量是最佳现金持有量",
      "B": "现金机会成本和短缺成本相等时的现金持有量是最佳现金持有量",
      "C": "现金机会成本最小时的现金持有量是最佳现金持有量",
      "D": "现金机会成本、管理成本和短缺成本之和最小时的现金持有量是最佳现金持有量"
    },
    "answer": "BD",
    "analysis": "企业持有现金会产生三种成本，分别为：机会成本、管理成本、短缺成本。三项成本之和最小的现金持有量就是最佳现金持有量，此时机会成本等于短缺成本，选项BD正确。",
    "source": {
      "question_text": "2019_财务成本管理_题目.txt",
      "answer_text": "2019_财务成本管理_答案.txt"
    }
  },
  {
    "year": 2019,
    "section_name": "多项选择题",
    "section_type": "multiple",
    "number": 9,
    "stem": "甲公司采用作业成本法，下列选项中，属于生产维持级作业库的有( )。",
    "options": {
      "A": "机器加工",
      "B": "工厂安保",
      "C": "行政管理",
      "D": "半成品检验"
    },
    "answer": "BC",
    "analysis": "生产维持级作业，是指服务于整个工厂的作业，例如工厂保安、维修、行政管理、保险、财产税等。它们是为了维护生产能力而进行的作业，不依赖于产品的数量、批次和种类，选项BC正确；机器加工属于产品级作业，半成品检验一般属于批次级作业，选项AD错误。",
    "source": {
      "question_text": "2019_财务成本管理_题目.txt",
      "answer_text": "2019_财务成本管理_答案.txt"
    }
  },
  {
    "year": 2019,
    "section_name": "多项选择题",
    "section_type": "multiple",
    "number": 10,
    "stem": "编制直接人工预算时，影响直接人工总成本的因素有( )。",
    "options": {
      "A": "预计产量",
      "B": "预计直接人工工资率",
      "C": "预计车间辅助人员工资",
      "D": "预计单位产品直接人工工时"
    },
    "answer": "ABD",
    "analysis": "直接人工预算是以生产预算为基础编制的，其中人工总成本=预计直接人工工资率×预计产量×预计单位产品直接人工工时，选项ABD正确。",
    "source": {
      "question_text": "2019_财务成本管理_题目.txt",
      "answer_text": "2019_财务成本管理_答案.txt"
    }
  },
  {
    "year": 2019,
    "section_name": "多项选择题",
    "section_type": "multiple",
    "number": 11,
    "stem": "下列各项关于经济增加值的说法中，正确的有( )。",
    "options": {
      "A": "经济增加值便于不同规模公司的业绩比较",
      "B": "经济增加值为正表明经营者为股东创造了价值",
      "C": "计算经济增加值使用的资本成本应随资本市场变化而调整",
      "D": "经济增加值是税后净营业利润扣除全部投入资本的成本后的剩余收益"
    },
    "answer": "BCD",
    "analysis": "由于经济增加值是绝对数指标，不便于比较不同规模公司的业绩，选项A错误。经济增加值=税后净营业利润-平均资本占用×加权平均资本成本。经济增加值是税后净营业利润扣除全部投入资本的成本后的剩余收益，其值为正表明经营者在为企业创造价值，选项BD正确。计算经济增加值时，需要根据资本市场的机会成本计算资本成本，以实现经济增加值与资本市场的衔接，选项C正确。",
    "source": {
      "question_text": "2019_财务成本管理_题目.txt",
      "answer_text": "2019_财务成本管理_答案.txt"
    }
  },
  {
    "year": 2019,
    "section_name": "多项选择题",
    "section_type": "multiple",
    "number": 12,
    "stem": "甲投资者同时买进一只股票的看涨期权和看跌期权，该投资策略适合的情形有( )。",
    "options": {
      "A": "预计标的股票市场价格将小幅下跌",
      "B": "预计标的股票市场价格将大幅上涨",
      "C": "预计标的股票市场价格将大幅下跌",
      "D": "预计标的股票市场价格将小幅上涨"
    },
    "answer": "BC",
    "analysis": "多头对敲是指同时买进一只股票的看涨期权和看跌期权，它们的执行价格、到期日都相同。多头对敲策略对于预计市场价格将发生剧烈变动，但是不知道升高还是降低的投资者非常有用，因此选项 BC正确。",
    "source": {
      "question_text": "2019_财务成本管理_题目.txt",
      "answer_text": "2019_财务成本管理_答案.txt"
    }
  },
  {
    "year": 2019,
    "section_name": "计算分析题",
    "section_type": "analysis",
    "number": 1,
    "stem": "甲公司是一家能源类上市公司,当年取得的利润在下年分配。2018年公司净利润10000万元，2019年分配现金股利3000万元。预计2019年净利润12000万元，2020年只投资一个新项目,总投资额8000万元。要求: （1）如果甲公司采用固定股利政策,计算2019年净利润的股利支付率。（2）如果甲公司采用固定股利支付率政策,计算2019年净利润的股利支付率。（3）如果甲公司采用剩余股利政策,目标资本结构是负债/权益等于2/3,计算2019年净利润的股利支付率。（4）如果甲公司采用低正常股利加外股利政策,低正常股利为2000万元,额外股利为2019年净利润扣除低正常股利后余额的16%,计算2019年净利润的股利支付率。（5）比较上述各种股利政策的优点和缺点。",
    "options": {},
    "answer": "",
    "analysis": "",
    "source": {
      "question_text": "2019_财务成本管理_题目.txt",
      "answer_text": "2019_财务成本管理_答案.txt"
    }
  },
  {
    "year": 2019,
    "section_name": "计算分析题",
    "section_type": "analysis",
    "number": 2,
    "stem": "甲汽车租赁公司拟购置一批新车用于出租。现有两种投资方案,相关信息如下: 方案一:购买中档轿车100辆,每辆车价格10万元,另需支付车辆价格10%的购置相关税费,每年平均出租 300天,日均租金150元/辆,车辆预计使用年限8年,8年后变现价值为0。前5年每年维护费2000元/辆,后3年每年维护费3000元/辆。车辆使用期间每年保险费3500元/辆,其他税费500元/辆。每年增加付现固定运营成本20.5万元。方案二:购买大型客车20辆,每辆车价格50万元,另需支付车辆价格10%购置相关税费。每年平均出租 250 天,日均租金840元/辆。车辆可使用年限10年,10 后变现价值为0。前6年每年维护费5000元/辆,后 4年每年维护费10000元/辆。车辆使用期间每年保险费30000元/辆,其他税费5000元/辆。每年增加付现固定运营成本10万元。根据税法相关规定,车辆购置相关税费计入车辆原值,采用直线计提折旧,无残值。等风险投资必要报酬率12%,企业所得稅税率25%。假设购车相关支出发生在年初,每年现金流入、现金流出均发生在年末。要求：（1）分别估计两个方案的现金流量。（2）分别计算两个方案的净现值。（3）分别计算两个方案净现值的等额年金。（4）假设两个方案都可以无限重置,且是互斥项目,用等额年金法判断甲公司应采用哪个投资方案。",
    "options": {},
    "answer": "",
    "analysis": "",
    "source": {
      "question_text": "2019_财务成本管理_题目.txt",
      "answer_text": "2019_财务成本管理_答案.txt"
    }
  },
  {
    "year": 2019,
    "section_name": "计算分析题",
    "section_type": "analysis",
    "number": 3,
    "stem": "甲公司是一家投资公司,拟于 2020年初以18000万元收购乙公司全部股权。为分析收购方案可行性,收集资料如下：（1）乙公司是一家传统汽车零部件制造企业,收购前处于稳定增长状态,增长率7.5%。2019年净利润 750万元，当年取得的利润在当年分配,股利支付率80%。2019年末(当年利润分配后)净经营资产4300万元,净负债2150万元。（2）收购后,甲公司将通过拓宽销售渠道、提高管理水平、降低成本费用等多种方式,提高乙公司的销售增长率和营业净利率。预计乙公司2020年营业收入6000万元,2021年营业收入比2020年增长 10%,2022年进入稳定增长状态,增长率8%。（3）收购后,预计乙公司相关财务比率保持稳定,具体如下: 营业成本/营业收入 65% 销售和管理费用/营业收入 15% 净经营资产/营业收入 70% 净负债/营业收入 30% 债务利息率 8% 企业所得税税率 25% （4）乙公司股票等风险投资必要报酬率收购前11.5%,收购后11%。（5）假设各年现金流量均发生在年末。要求：（1）如果不收购,采用股利现金流量折现模型,估计2020年初乙公司股权价值。（2）如果收购,釆用股权现金流量折现模型,估计2020年初乙公司股权价值(计算过程和结果填入下方表格中)。单位：万元 2020年 2021年 2022年股权现金流量股权价值 （3）计算该收购产生的控股权溢价、为乙公司原股东带来的净现值、为甲公司带来的净现值。（4）判断甲公司收购是否可行,并简要说明理由。",
    "options": {},
    "answer": "",
    "analysis": "",
    "source": {
      "question_text": "2019_财务成本管理_题目.txt",
      "answer_text": "2019_财务成本管理_答案.txt"
    }
  },
  {
    "year": 2019,
    "section_name": "计算分析题",
    "section_type": "analysis",
    "number": 4,
    "stem": "甲公司下属乙部门生产A 产品,全年生产能量 1200000 机器工时,单位产品标准机器工时 120 小时。2018年实际产量11000件,实际耗用机器工时1331000小时。2018年标准成本资料如下: （1）直接材料标准消耗10千克/件,标准价格22元/千克; （2）变动制造费用预算3600000元; （3）固定制造费用预算2160000元。2018年完全成本法下的实际成本资料如下: （1）直接材料实际耗用121000千克,实际价格24元/千克; （2）变动制造费用实际4126100元; （3）固定制造费用实际2528900元。该部门作为成本中心,一直采用标准成本法控制成本和考核业绩。最近,新任部门经理提出,按完全成本法下的标准成本考核业绩不合理,建议公司调整组织结构,将销售部门和生产部门合并为事业部,采用部门可控边际贡献考核经理业绩。目前,该产品年销售10000件,每件售价1000元。经分析,40%的固定制造费用为部门可控成本,60%的固定制造费用为部门不可控成本。要求: （1）计算A产品的单位标准成本和单位实际成本。（2） 分别计算A产品总成本的直接材料的价格差异和数量差异、变动制造费用的价格差异和数量差异,用三因素分析法计算固定制造费用的耗费差异、闲置能量差异和效率差异,并指出各项差异是有利差异和不利差异。（3）计算乙部门实际的部门可控边际贡献。",
    "options": {},
    "answer": "",
    "analysis": "",
    "source": {
      "question_text": "2019_财务成本管理_题目.txt",
      "answer_text": "2019_财务成本管理_答案.txt"
    }
  },
  {
    "year": 2019,
    "section_name": "计算分析题",
    "section_type": "analysis",
    "number": 5,
    "stem": "甲公司乙部门只生产一种产品,投资额 25000万元,2019年销售 500万件。该产品单价25元,单位变动成本资料如下：项目单位变动成本（元） 直接材料 3 直接人工 4 变动制造费用 2 变动销售费用 1 合计 10 该产品目前盈亏临界点作业率 20%,现有产能已满负荷运转。因产品供不应求,为提高销量,公司经可行性研究,2020年拟增加50000万元投资。新产能投入运营后,每年增加2700万元固定成本。假设公司产销平衡,不考虑企业所得税。要求：（1）计算乙部门2019年税前投资报酬率;假设产能扩张不影响产品单位边际贡献,为达到2019年税前投资报酬率水平,计算2020年应实现的销量。（2）计算乙部门2019年经营杠杆系数;假设产能扩张不影响产品单位边际贡献,为达到2019年经营杠杆水平,计算2020年应实现的销量。",
    "options": {},
    "answer": "",
    "analysis": "",
    "source": {
      "question_text": "2019_财务成本管理_题目.txt",
      "answer_text": "2019_财务成本管理_答案.txt"
    }
  }
]